setup.py
cassandra_helpers/__init__.py
cassandra_helpers/connectable.py
cassandra_helpers/keyspace.py
cassandra_helpers/models.py
cassandra_helpers.egg-info/PKG-INFO
cassandra_helpers.egg-info/SOURCES.txt
cassandra_helpers.egg-info/dependency_links.txt
cassandra_helpers.egg-info/requires.txt
cassandra_helpers.egg-info/top_level.txt