Metadata-Version: 1.1
Name: cassandra-helpers
Version: 0.0.0
Summary: Helper functions for comfortable working with cassandra-driver.
Home-page: https://github.com/lycantropos/cassandra_helpers
Author: Azat Ibrakov
Author-email: azatibrakov@gmail.com
License: UNKNOWN
Download-URL: https://github.com/lycantropos/cassandra_helpers/archive/master.tar.gz
Keywords: Cassandra
Platform: UNKNOWN
